odoo8_addon_attachment_edit-8.0.1.0.0.99.dev8-py2.7-nspkg.pth
odoo8_addon_attachment_edit-8.0.1.0.0.99.dev8.dist-info/METADATA
odoo8_addon_attachment_edit-8.0.1.0.0.99.dev8.dist-info/RECORD
odoo8_addon_attachment_edit-8.0.1.0.0.99.dev8.dist-info/WHEEL
odoo8_addon_attachment_edit-8.0.1.0.0.99.dev8.dist-info/namespace_packages.txt
odoo8_addon_attachment_edit-8.0.1.0.0.99.dev8.dist-info/top_level.txt
odoo_addons/attachment_edit/README.rst
odoo_addons/attachment_edit/__init__.py
odoo_addons/attachment_edit/__openerp__.py
odoo_addons/attachment_edit/i18n/de.po
odoo_addons/attachment_edit/i18n/it.po
odoo_addons/attachment_edit/i18n/sl.po
odoo_addons/attachment_edit/i18n/zh_CN.po
odoo_addons/attachment_edit/models/__init__.py
odoo_addons/attachment_edit/models/ir_attachment.py
odoo_addons/attachment_edit/static/description/icon.png
odoo_addons/attachment_edit/static/src/js/attachment_edit.js
odoo_addons/attachment_edit/static/src/xml/attachment_edit.xml
odoo_addons/attachment_edit/views/ir_attachment.xml
odoo_addons/attachment_edit/views/templates.xml
